sdk/__init__.py
sdk/api_client.py
sdk/image_generation.py
tests/__init__.py
tests/test_image_generation.py
InstantLight_sdk-0.1.0.dist-info/LICENSE
InstantLight_sdk-0.1.0.dist-info/METADATA
InstantLight_sdk-0.1.0.dist-info/WHEEL
InstantLight_sdk-0.1.0.dist-info/top_level.txt
InstantLight_sdk-0.1.0.dist-info/RECORD
