Metadata-Version: 2.1
Name: InstantLight-sdk
Version: 0.1.0
Summary: A Python SDK for your API
Home-page: https://github.com/yourusername/your_sdk
Author: Your Name
Author-email: your.email@example.com
Classifier: Programming Language :: Python :: 3
Classifier: License :: OSI Approved :: MIT License
Classifier: Operating System :: OS Independent
Requires-Python: >=3.6
License-File: LICENSE
Requires-Dist: requests
